[
  {
    "box": [
      0.46360015869140625,
      850.7407836914062,
      240.8824462890625,
      1077.9888916015625
    ],
    "class": "car",
    "score": 0.9289035201072693,
    "detailed_caption": "A silver car is seen in this surveillance image.",
    "class_detailed": "police car"
  },
  {
    "box": [
      948.7857055664062,
      206.05169677734375,
      1060.2734375,
      278.703125
    ],
    "class": "bus",
    "score": 0.8715665936470032,
    "detailed_caption": "a group of people walking down a street next to a bus",
    "class_detailed": "bus"
  },
  {
    "box": [
      883.0557861328125,
      194.7835235595703,
      956.3111572265625,
      253.0997772216797
    ],
    "class": "bus",
    "score": 0.8250561356544495,
    "detailed_caption": "train",
    "class_detailed": "bus"
  },
  {
    "box": [
      724.8370971679688,
      734.3663330078125,
      774.9948120117188,
      810.2890014648438
    ],
    "class": "fire hydrant",
    "score": 0.7809188961982727,
    "detailed_caption": "fire hydrant in red shirt",
    "class_detailed": "fire hydrant"
  },
  {
    "box": [
      298.606201171875,
      185.52200317382812,
      339.8235168457031,
      279.1307373046875
    ],
    "class": "traffic light",
    "score": 0.7070306539535522,
    "detailed_caption": "refrigerator",
    "class_detailed": "traffic light"
  },
  {
    "box": [
      395.572265625,
      179.87237548828125,
      427.55841064453125,
      254.76278686523438
    ],
    "class": "traffic light",
    "score": 0.6941302418708801,
    "detailed_caption": "refrigerator",
    "class_detailed": "traffic light"
  },
  {
    "box": [
      352.8868408203125,
      185.0144805908203,
      392.1196594238281,
      276.96234130859375
    ],
    "class": "traffic light",
    "score": 0.6408119797706604,
    "detailed_caption": "suitcase with three compartments in a room",
    "class_detailed": "traffic light"
  },
  {
    "box": [
      1247.0517578125,
      167.39602661132812,
      1280.7784423828125,
      212.5631103515625
    ],
    "class": "traffic light",
    "score": 0.5929158329963684,
    "detailed_caption": "person",
    "class_detailed": "traffic light"
  },
  {
    "box": [
      425.7410888671875,
      375.678955078125,
      457.6904296875,
      406.2806396484375
    ],
    "class": "traffic light",
    "score": 0.5612779259681702,
    "detailed_caption": "person",
    "class_detailed": "traffic light"
  }
]